onc/__init__.py
onc/onc.py
onc/modules/_DataProductFile.py
onc/modules/_MultiPage.py
onc/modules/_OncArchive.py
onc/modules/_OncDelivery.py
onc/modules/_OncDiscovery.py
onc/modules/_OncRealTime.py
onc/modules/_OncService.py
onc/modules/_PollLog.py
onc/modules/__init__.py
onc/modules/_util.py
onc/util/__init__.py
onc/util/util.py
onc-2.6.0.dist-info/licenses/LICENSE.txt
onc-2.6.0.dist-info/METADATA
onc-2.6.0.dist-info/WHEEL
onc-2.6.0.dist-info/top_level.txt
onc-2.6.0.dist-info/RECORD
