Metadata-Version: 2.4
Name: onc
Version: 2.6.0
Summary: Oceans 3.0 API Python Client Library
Author-email: ONC Data Team <api_support@oceannetworks.ca>
License:                                  Apache License
Project-URL: Homepage, https://data.oceannetworks.ca/OpenAPI
Project-URL: Documentation, https://oceannetworkscanada.github.io/api-python-client/
Project-URL: Source, https://github.com/OceanNetworksCanada/api-python-client
Classifier: Development Status :: 5 - Production/Stable
Classifier: Intended Audience :: Science/Research
Classifier: License :: OSI Approved :: Apache Software License
Classifier: Operating System :: OS Independent
Classifier: Programming Language :: Python :: 3
Classifier: Topic :: Scientific/Engineering
Requires-Python: >=3.10
License-File: LICENSE.txt
Requires-Dist: requests
Requires-Dist: python-dateutil
Requires-Dist: humanize
Provides-Extra: dev
Requires-Dist: ipykernel; extra == "dev"
Requires-Dist: python-dotenv; extra == "dev"
Requires-Dist: tox; extra == "dev"
Requires-Dist: black; extra == "dev"
Requires-Dist: isort; extra == "dev"
Requires-Dist: pytest; extra == "dev"
Requires-Dist: pytest-cov; extra == "dev"
Requires-Dist: ruff; extra == "dev"
Provides-Extra: doc
Requires-Dist: myst-nb; extra == "doc"
Requires-Dist: sphinx-autoapi; extra == "doc"
Requires-Dist: sphinx-rtd-theme; extra == "doc"
Requires-Dist: sphinx-autobuild; extra == "doc"
Requires-Dist: sphinx_copybutton; extra == "doc"
Requires-Dist: pandas; extra == "doc"
Requires-Dist: python-dotenv; extra == "doc"
Requires-Dist: black[jupyter]; extra == "doc"
Requires-Dist: ipykernel; extra == "doc"
Requires-Dist: tox; extra == "doc"
Requires-Dist: jupytext; extra == "doc"
Provides-Extra: regression
Requires-Dist: jupytext; extra == "regression"
Requires-Dist: pytest; extra == "regression"
Requires-Dist: python-dotenv; extra == "regression"
Requires-Dist: pandas; extra == "regression"
Dynamic: license-file
